vlc_rm/__init__.py
vlc_rm/__main__.py
vlc_rm/_version.py
vlc_rm/cli.py
vlc_rm/constants.py
vlc_rm/indoorenv.py
vlc_rm/photodetector.py
vlc_rm/recursivemodel.py
vlc_rm/ser.py
vlc_rm/transmitter.py
vlc_rm/sensors/ResponsivityS10917-35GT.txt
vlc_rm/sensors/ResponsivityTCS3103-04.txt
vlc_rm-0.1.dev196.dist-info/AUTHORS.rst
vlc_rm-0.1.dev196.dist-info/LICENSE
vlc_rm-0.1.dev196.dist-info/METADATA
vlc_rm-0.1.dev196.dist-info/WHEEL
vlc_rm-0.1.dev196.dist-info/entry_points.txt
vlc_rm-0.1.dev196.dist-info/top_level.txt
vlc_rm-0.1.dev196.dist-info/RECORD
