Metadata-Version: 2.1
Name: vlc-rm
Version: 0.1.dev196
Summary: The package implements a recursive model to simulate a VLC system inside of rectangular empty room.
Home-page: https://github.com/jufgutierrezgo/python-vlc-rm
Author: Juan F. Gutierrez
Author-email: jufgutierrezgo@unal.edu.co
License: BSD-3-Clause
Project-URL: Documentation, https://python-vlc-rm.readthedocs.io/
Project-URL: Changelog, https://python-vlc-rm.readthedocs.io/en/latest/changelog.html
Project-URL: Issue Tracker, https://github.com/jufgutierrezgo/python-vlc-rm/issues
Classifier: Development Status :: 5 - Production/Stable
Classifier: Intended Audience :: Developers
Classifier: License :: OSI Approved :: BSD License
Classifier: Operating System :: Unix
Classifier: Operating System :: POSIX
Classifier: Operating System :: Microsoft :: Windows
Classifier: Programming Language :: Python
Classifier: Programming Language :: Python :: 3
Classifier: Programming Language :: Python :: 3 :: Only
Classifier: Programming Language :: Python :: 3.7
Classifier: Programming Language :: Python :: 3.8
Classifier: Programming Language :: Python :: 3.9
Classifier: Programming Language :: Python :: 3.10
Classifier: Programming Language :: Python :: 3.11
Classifier: Programming Language :: Python :: Implementation :: CPython
Classifier: Programming Language :: Python :: Implementation :: PyPy
Classifier: Topic :: Utilities
Requires-Python: >=3.7
License-File: LICENSE
License-File: AUTHORS.rst
